{
  "date": "2026-05-10",
  "created_at": "2026-05-10T22:40:20",
  "lotteries": {
    "fc3d": {
      "name": "中国福利彩票 3D",
      "source": "https://touch.17500.cn/award/history/lotid/3d.html",
      "history_count": 29,
      "latest_issue": "2026119",
      "latest_date": "2026-05-09",
      "latest_number": "112",
      "weights": {
        "frequency": 0.34,
        "recency": 0.28,
        "omission": 0.22,
        "transition": 0.16
      },
      "model_weights": {
        "legacy": 0.1934,
        "markov": 0.2153,
        "bayes": 0.2061,
        "shape": 0.3852
      },
      "trend_summary": {
        "recent_window": 29,
        "sum_avg": 12.66,
        "sum_last": 4,
        "span_avg": 4.72,
        "span_last": 1,
        "most_common_odd_count": 1,
        "most_common_big_count": 2,
        "hot_sum_tails": [
          [
            4,
            7
          ],
          [
            7,
            4
          ],
          [
            9,
            4
          ]
        ]
      },
      "pre_draw_signals": {
        "source": "https://www.17500.cn/",
        "issue_hint": "120",
        "draw_number": "120",
        "machine_number": "373",
        "test_number": "820",
        "focus_number": "528"
      },
      "expert_signals": {
        "source_names": [
          "17500 钱王点评",
          "17500 孟庆会一语定胆"
        ],
        "source_urls": [
          "https://www.17500.cn/search/457.html",
          "https://www.17500.cn/search/921.html"
        ],
        "banker_digits": [
          0,
          1,
          2,
          3,
          4,
          5,
          6,
          7,
          8,
          9
        ],
        "hot_digits": [
          1,
          3,
          7
        ],
        "kill_digits": [
          0,
          2,
          5,
          6
        ],
        "sum_ranges": [
          [
            0,
            26
          ],
          [
            4,
            26
          ],
          [
            5,
            26
          ]
        ],
        "span_values": [
          0,
          1,
          3,
          5,
          7
        ],
        "snippets": [
          "字谜 学习彩票 彩皇网 足球 福彩3D 双色球 快乐8 七乐彩 排列3 排列5 大乐透 7星彩 全国彩票 六省联销 福彩15选5 东方6+1 上海 上海15选5 上",
          "字谜] 福彩3D第2026119期黑胆王中奖迷 黑胆王中奖迷 119期福彩3d黑胆王中奖迷：野老闲云自在身 118期福彩3d黑胆王中奖迷：卖膏药吹治疮痕 开：1 3",
          "和值：6 117期福 ... 2026-05-08 22:27 [3D字谜] 福彩3D第2026113期黑胆王中奖迷 黑胆王中奖迷 113期福彩3d黑胆王中奖迷：铁",
          "字谜_乐彩网 [登录/注册] 手机乐彩网 扫码|点击 访问手机乐彩网 乐彩网APP 扫码下载乐彩网安卓APP 下载 查看 网站地图 联系客服 在线客服 400801",
          "字谜 学习彩票 彩皇网 足球 福彩3D 双色球 快乐8 七乐彩 排列3 排列5 大乐透 7星彩 全国彩票 六省联销 福彩15选5 东方6+1 上海 上海15选5 上"
        ],
        "weight": 0.0711
      },
      "candidates": [
        {
          "rank": 1,
          "number": "671",
          "score": -5.00168,
          "sum": 14,
          "span": 6,
          "models": {
            "legacy": -6.6037,
            "markov": -6.5153,
            "bayes": -5.7974,
            "shape": -2.9256
          }
        },
        {
          "rank": 2,
          "number": "312",
          "score": -5.271417,
          "sum": 6,
          "span": 2,
          "models": {
            "legacy": -7.5243,
            "markov": -5.5612,
            "bayes": -6.5718,
            "shape": -3.2825
          }
        },
        {
          "rank": 3,
          "number": "411",
          "score": -5.144945,
          "sum": 6,
          "span": 3,
          "models": {
            "legacy": -7.5067,
            "markov": -6.1753,
            "bayes": -5.3332,
            "shape": -3.2825
          }
        },
        {
          "rank": 4,
          "number": "518",
          "score": -5.009948,
          "sum": 14,
          "span": 7,
          "models": {
            "legacy": -6.7367,
            "markov": -6.7624,
            "bayes": -5.4546,
            "shape": -2.9256
          }
        },
        {
          "rank": 5,
          "number": "581",
          "score": -5.065402,
          "sum": 14,
          "span": 7,
          "models": {
            "legacy": -6.9081,
            "markov": -6.5153,
            "bayes": -5.8209,
            "shape": -2.9256
          }
        },
        {
          "rank": 6,
          "number": "811",
          "score": -5.146351,
          "sum": 10,
          "span": 7,
          "models": {
            "legacy": -7.0257,
            "markov": -6.1753,
            "bayes": -5.3402,
            "shape": -3.524
          }
        },
        {
          "rank": 7,
          "number": "872",
          "score": -5.150093,
          "sum": 17,
          "span": 6,
          "models": {
            "legacy": -6.6489,
            "markov": -6.5153,
            "bayes": -5.8079,
            "shape": -3.2825
          }
        },
        {
          "rank": 8,
          "number": "812",
          "score": -5.159179,
          "sum": 11,
          "span": 7,
          "models": {
            "legacy": -6.8919,
            "markov": -6.1753,
            "bayes": -5.5279,
            "shape": -3.524
          }
        },
        {
          "rank": 9,
          "number": "612",
          "score": -5.171052,
          "sum": 9,
          "span": 5,
          "models": {
            "legacy": -6.7644,
            "markov": -6.1753,
            "bayes": -5.7052,
            "shape": -3.524
          }
        },
        {
          "rank": 10,
          "number": "171",
          "score": -5.171178,
          "sum": 9,
          "span": 6,
          "models": {
            "legacy": -6.8346,
            "markov": -5.9013,
            "bayes": -5.9262,
            "shape": -3.524
          }
        },
        {
          "rank": 11,
          "number": "818",
          "score": -5.19186,
          "sum": 17,
          "span": 7,
          "models": {
            "legacy": -6.9946,
            "markov": -6.7624,
            "bayes": -5.428,
            "shape": -3.2825
          }
        },
        {
          "rank": 12,
          "number": "572",
          "score": -5.201211,
          "sum": 14,
          "span": 5,
          "models": {
            "legacy": -6.404,
            "markov": -6.5153,
            "bayes": -5.8345,
            "shape": -3.524
          }
        },
        {
          "rank": 13,
          "number": "172",
          "score": -5.212019,
          "sum": 10,
          "span": 6,
          "models": {
            "legacy": -6.8457,
            "markov": -5.9013,
            "bayes": -6.1139,
            "shape": -3.524
          }
        },
        {
          "rank": 14,
          "number": "511",
          "score": -5.220843,
          "sum": 7,
          "span": 4,
          "models": {
            "legacy": -7.3825,
            "markov": -6.1753,
            "bayes": -5.3668,
            "shape": -3.524
          }
        },
        {
          "rank": 15,
          "number": "571",
          "score": -5.225336,
          "sum": 13,
          "span": 6,
          "models": {
            "legacy": -6.7288,
            "markov": -6.5153,
            "bayes": -5.6468,
            "shape": -3.524
          }
        },
        {
          "rank": 16,
          "number": "871",
          "score": -5.234314,
          "sum": 16,
          "span": 7,
          "models": {
            "legacy": -6.8035,
            "markov": -6.5153,
            "bayes": -5.6202,
            "shape": -3.524
          }
        },
        {
          "rank": 17,
          "number": "412",
          "score": -5.234948,
          "sum": 7,
          "span": 3,
          "models": {
            "legacy": -7.2911,
            "markov": -6.1753,
            "bayes": -5.5209,
            "shape": -3.524
          }
        },
        {
          "rank": 18,
          "number": "512",
          "score": -5.239759,
          "sum": 8,
          "span": 4,
          "models": {
            "legacy": -7.2803,
            "markov": -6.1753,
            "bayes": -5.5545,
            "shape": -3.524
          }
        },
        {
          "rank": 19,
          "number": "611",
          "score": -5.241144,
          "sum": 8,
          "span": 5,
          "models": {
            "legacy": -7.3269,
            "markov": -6.1753,
            "bayes": -5.5174,
            "shape": -3.524
          }
        },
        {
          "rank": 20,
          "number": "418",
          "score": -5.247258,
          "sum": 13,
          "span": 7,
          "models": {
            "legacy": -7.2885,
            "markov": -6.7624,
            "bayes": -5.421,
            "shape": -3.2825
          }
        }
      ],
      "top3": [
        {
          "rank": 1,
          "number": "671",
          "score": -5.00168,
          "sum": 14,
          "span": 6,
          "models": {
            "legacy": -6.6037,
            "markov": -6.5153,
            "bayes": -5.7974,
            "shape": -2.9256
          }
        },
        {
          "rank": 2,
          "number": "312",
          "score": -5.271417,
          "sum": 6,
          "span": 2,
          "models": {
            "legacy": -7.5243,
            "markov": -5.5612,
            "bayes": -6.5718,
            "shape": -3.2825
          }
        },
        {
          "rank": 3,
          "number": "411",
          "score": -5.144945,
          "sum": 6,
          "span": 3,
          "models": {
            "legacy": -7.5067,
            "markov": -6.1753,
            "bayes": -5.3332,
            "shape": -3.2825
          }
        }
      ],
      "note": "随机开奖不可预测，本结果仅用于统计记录和复盘。"
    },
    "pls": {
      "name": "中国体育彩票 排列三",
      "source": "https://touch.17500.cn/award/history/lotid/pl3.html",
      "history_count": 29,
      "latest_issue": "2026119",
      "latest_date": "2026-05-09",
      "latest_number": "222",
      "weights": {
        "frequency": 0.34,
        "recency": 0.28,
        "omission": 0.22,
        "transition": 0.16
      },
      "model_weights": {
        "legacy": 0.1926,
        "markov": 0.2152,
        "bayes": 0.2025,
        "shape": 0.3897
      },
      "trend_summary": {
        "recent_window": 29,
        "sum_avg": 13.14,
        "sum_last": 6,
        "span_avg": 4.48,
        "span_last": 0,
        "most_common_odd_count": 2,
        "most_common_big_count": 1,
        "hot_sum_tails": [
          [
            0,
            10
          ],
          [
            6,
            4
          ],
          [
            9,
            4
          ]
        ]
      },
      "pre_draw_signals": {
        "source": "https://www.17500.cn/",
        "issue_hint": "120",
        "draw_number": "120",
        "machine_number": "373",
        "test_number": "820",
        "focus_number": "528"
      },
      "expert_signals": {},
      "candidates": [
        {
          "rank": 1,
          "number": "901",
          "score": -4.92302,
          "sum": 10,
          "span": 9,
          "models": {
            "legacy": -6.6549,
            "markov": -5.5284,
            "bayes": -6.112,
            "shape": -3.1149
          }
        },
        {
          "rank": 2,
          "number": "252",
          "score": -5.321967,
          "sum": 9,
          "span": 3,
          "models": {
            "legacy": -6.997,
            "markov": -6.62,
            "bayes": -5.7455,
            "shape": -3.5573
          }
        },
        {
          "rank": 3,
          "number": "271",
          "score": -4.996029,
          "sum": 10,
          "span": 6,
          "models": {
            "legacy": -6.2353,
            "markov": -5.9854,
            "bayes": -6.0071,
            "shape": -3.3118
          }
        },
        {
          "rank": 4,
          "number": "272",
          "score": -5.093657,
          "sum": 11,
          "span": 5,
          "models": {
            "legacy": -6.7673,
            "markov": -5.9854,
            "bayes": -5.9831,
            "shape": -3.3118
          }
        },
        {
          "rank": 5,
          "number": "952",
          "score": -5.13751,
          "sum": 16,
          "span": 7,
          "models": {
            "legacy": -6.5156,
            "markov": -6.62,
            "bayes": -5.7647,
            "shape": -3.3118
          }
        },
        {
          "rank": 6,
          "number": "902",
          "score": -5.163412,
          "sum": 11,
          "span": 9,
          "models": {
            "legacy": -7.0331,
            "markov": -5.5284,
            "bayes": -6.0881,
            "shape": -3.5573
          }
        },
        {
          "rank": 7,
          "number": "072",
          "score": -5.225509,
          "sum": 9,
          "span": 7,
          "models": {
            "legacy": -7.1442,
            "markov": -5.9854,
            "bayes": -6.2759,
            "shape": -3.3118
          }
        },
        {
          "rank": 8,
          "number": "922",
          "score": -5.235234,
          "sum": 13,
          "span": 7,
          "models": {
            "legacy": -6.495,
            "markov": -6.62,
            "bayes": -5.7946,
            "shape": -3.5573
          }
        },
        {
          "rank": 9,
          "number": "292",
          "score": -5.26997,
          "sum": 13,
          "span": 7,
          "models": {
            "legacy": -6.6633,
            "markov": -6.62,
            "bayes": -5.8061,
            "shape": -3.5573
          }
        },
        {
          "rank": 10,
          "number": "091",
          "score": -5.279116,
          "sum": 10,
          "span": 9,
          "models": {
            "legacy": -7.2729,
            "markov": -6.62,
            "bayes": -6.1228,
            "shape": -3.1149
          }
        },
        {
          "rank": 11,
          "number": "972",
          "score": -5.280829,
          "sum": 18,
          "span": 7,
          "models": {
            "legacy": -7.2222,
            "markov": -5.9854,
            "bayes": -6.0024,
            "shape": -3.5573
          }
        },
        {
          "rank": 12,
          "number": "071",
          "score": -5.289705,
          "sum": 8,
          "span": 7,
          "models": {
            "legacy": -7.4523,
            "markov": -5.9854,
            "bayes": -6.2998,
            "shape": -3.3118
          }
        },
        {
          "rank": 13,
          "number": "207",
          "score": -5.299027,
          "sum": 9,
          "span": 7,
          "models": {
            "legacy": -7.5772,
            "markov": -6.1156,
            "bayes": -6.0887,
            "shape": -3.3118
          }
        },
        {
          "rank": 14,
          "number": "921",
          "score": -5.302346,
          "sum": 12,
          "span": 8,
          "models": {
            "legacy": -6.8182,
            "markov": -6.62,
            "bayes": -5.8186,
            "shape": -3.5573
          }
        },
        {
          "rank": 15,
          "number": "372",
          "score": -5.334261,
          "sum": 12,
          "span": 5,
          "models": {
            "legacy": -6.9768,
            "markov": -5.9854,
            "bayes": -6.4997,
            "shape": -3.5573
          }
        },
        {
          "rank": 16,
          "number": "291",
          "score": -5.337082,
          "sum": 12,
          "span": 8,
          "models": {
            "legacy": -6.9865,
            "markov": -6.62,
            "bayes": -5.8301,
            "shape": -3.5573
          }
        },
        {
          "rank": 17,
          "number": "702",
          "score": -5.338314,
          "sum": 9,
          "span": 7,
          "models": {
            "legacy": -7.5212,
            "markov": -5.5284,
            "bayes": -6.96,
            "shape": -3.3118
          }
        },
        {
          "rank": 18,
          "number": "951",
          "score": -5.338353,
          "sum": 15,
          "span": 8,
          "models": {
            "legacy": -7.5332,
            "markov": -6.62,
            "bayes": -5.7887,
            "shape": -3.3118
          }
        },
        {
          "rank": 19,
          "number": "251",
          "score": -5.344164,
          "sum": 8,
          "span": 4,
          "models": {
            "legacy": -7.087,
            "markov": -6.62,
            "bayes": -5.7694,
            "shape": -3.5573
          }
        },
        {
          "rank": 20,
          "number": "202",
          "score": -5.35135,
          "sum": 4,
          "span": 2,
          "models": {
            "legacy": -8.5259,
            "markov": -5.5284,
            "bayes": -6.0688,
            "shape": -3.3118
          }
        }
      ],
      "top3": [
        {
          "rank": 1,
          "number": "901",
          "score": -4.92302,
          "sum": 10,
          "span": 9,
          "models": {
            "legacy": -6.6549,
            "markov": -5.5284,
            "bayes": -6.112,
            "shape": -3.1149
          }
        },
        {
          "rank": 2,
          "number": "252",
          "score": -5.321967,
          "sum": 9,
          "span": 3,
          "models": {
            "legacy": -6.997,
            "markov": -6.62,
            "bayes": -5.7455,
            "shape": -3.5573
          }
        },
        {
          "rank": 3,
          "number": "271",
          "score": -4.996029,
          "sum": 10,
          "span": 6,
          "models": {
            "legacy": -6.2353,
            "markov": -5.9854,
            "bayes": -6.0071,
            "shape": -3.3118
          }
        }
      ],
      "note": "随机开奖不可预测，本结果仅用于统计记录和复盘。"
    },
    "plw": {
      "name": "中国体育彩票 排列五",
      "source": "https://touch.17500.cn/award/history/lotid/pl5.html",
      "history_count": 29,
      "latest_issue": "2026119",
      "latest_date": "2026-05-09",
      "latest_number": "22219",
      "weights": {
        "frequency": 0.34,
        "recency": 0.28,
        "omission": 0.22,
        "transition": 0.16
      },
      "model_weights": {
        "legacy": 0.1929,
        "markov": 0.2011,
        "bayes": 0.1896,
        "shape": 0.4164
      },
      "trend_summary": {
        "recent_window": 29,
        "sum_avg": 21.1,
        "sum_last": 16,
        "span_avg": 6.79,
        "span_last": 8,
        "most_common_odd_count": 3,
        "most_common_big_count": 2,
        "hot_sum_tails": [
          [
            8,
            5
          ],
          [
            9,
            5
          ],
          [
            2,
            4
          ]
        ]
      },
      "pre_draw_signals": {
        "source": "https://www.17500.cn/",
        "issue_hint": "120",
        "machine_number": "37312",
        "test_number": "82012",
        "focus_number": "52812"
      },
      "expert_signals": {
        "source_names": [
          "17500 排列五专家杀码"
        ],
        "source_urls": [
          "https://www.17500.cn/search/?wd=%E6%8E%92%E5%88%97%E4%BA%94%20%E6%9D%80%E4%B8%80%E7%A0%81"
        ],
        "banker_digits": [],
        "hot_digits": [],
        "kill_digits": [],
        "sum_ranges": [],
        "span_values": [],
        "snippets": [
          "字谜 学习彩票 彩皇网 足球 福彩3D 双色球 快乐8 七乐彩 排列3 排列5 大乐透 7星彩 全国彩票 六省联销 福彩15选5 东方6+1 上海 上海15选5 上",
          "字谜 图谜 条件 廊坊鸿运 949499 2.00元 阿郎赫赫哩呐 爱心角落 白鱼舟 铂金彩D 彩多星 重庆陈哥 潮人永恒22 大光光 带子入朝 福娃债主 奉旨拿奖",
          "和值预测 和尾预测 跨度预测 胆码预测 定位分析 号码预测 投注技巧 推荐 专家杀号 机选 选号 于海滨杀码 钱王点评 詹天佑点评 开奖号 胆拖 复式玩法 开奖信息"
        ],
        "weight": 0.0711
      },
      "candidates": [
        {
          "rank": 1,
          "number": "97213",
          "score": -6.859125,
          "sum": 22,
          "span": 8,
          "models": {
            "legacy": -8.542,
            "markov": -10.0625,
            "bayes": -9.418,
            "shape": -3.3673
          }
        },
        {
          "rank": 2,
          "number": "90201",
          "score": -7.388691,
          "sum": 12,
          "span": 9,
          "models": {
            "legacy": -11.4796,
            "markov": -8.716,
            "bayes": -10.6506,
            "shape": -3.3673
          }
        },
        {
          "rank": 3,
          "number": "25213",
          "score": -7.400746,
          "sum": 13,
          "span": 4,
          "models": {
            "legacy": -10.3947,
            "markov": -10.6971,
            "bayes": -9.161,
            "shape": -3.6203
          }
        },
        {
          "rank": 4,
          "number": "27193",
          "score": -7.002298,
          "sum": 22,
          "span": 8,
          "models": {
            "legacy": -8.9706,
            "markov": -10.0625,
            "bayes": -9.7371,
            "shape": -3.3673
          }
        },
        {
          "rank": 5,
          "number": "90193",
          "score": -7.041096,
          "sum": 22,
          "span": 9,
          "models": {
            "legacy": -9.545,
            "markov": -9.6056,
            "bayes": -9.842,
            "shape": -3.3673
          }
        },
        {
          "rank": 6,
          "number": "99211",
          "score": -7.085019,
          "sum": 22,
          "span": 8,
          "models": {
            "legacy": -9.3099,
            "markov": -10.2721,
            "bayes": -9.6058,
            "shape": -3.3673
          }
        },
        {
          "rank": 7,
          "number": "97231",
          "score": -7.094825,
          "sum": 22,
          "span": 8,
          "models": {
            "legacy": -9.5392,
            "markov": -9.6376,
            "bayes": -10.0973,
            "shape": -3.3673
          }
        },
        {
          "rank": 8,
          "number": "20293",
          "score": -7.116496,
          "sum": 16,
          "span": 9,
          "models": {
            "legacy": -9.9784,
            "markov": -9.6056,
            "bayes": -9.7988,
            "shape": -3.3673
          }
        },
        {
          "rank": 9,
          "number": "92113",
          "score": -7.187001,
          "sum": 16,
          "span": 8,
          "models": {
            "legacy": -9.2148,
            "markov": -10.6971,
            "bayes": -9.2341,
            "shape": -3.6203
          }
        },
        {
          "rank": 10,
          "number": "92191",
          "score": -7.198263,
          "sum": 22,
          "span": 8,
          "models": {
            "legacy": -9.5947,
            "markov": -10.2721,
            "bayes": -9.9134,
            "shape": -3.3673
          }
        },
        {
          "rank": 11,
          "number": "29113",
          "score": -7.221639,
          "sum": 16,
          "span": 8,
          "models": {
            "legacy": -9.3831,
            "markov": -10.6971,
            "bayes": -9.2456,
            "shape": -3.6203
          }
        },
        {
          "rank": 12,
          "number": "29191",
          "score": -7.232901,
          "sum": 22,
          "span": 8,
          "models": {
            "legacy": -9.7629,
            "markov": -10.2721,
            "bayes": -9.9249,
            "shape": -3.3673
          }
        },
        {
          "rank": 13,
          "number": "97123",
          "score": -7.236944,
          "sum": 22,
          "span": 8,
          "models": {
            "legacy": -9.4906,
            "markov": -10.6911,
            "bayes": -9.779,
            "shape": -3.3673
          }
        },
        {
          "rank": 14,
          "number": "27291",
          "score": -7.244826,
          "sum": 21,
          "span": 8,
          "models": {
            "legacy": -9.7897,
            "markov": -9.6376,
            "bayes": -10.078,
            "shape": -3.6203
          }
        },
        {
          "rank": 15,
          "number": "95233",
          "score": -7.254183,
          "sum": 22,
          "span": 7,
          "models": {
            "legacy": -9.3069,
            "markov": -10.6971,
            "bayes": -9.4947,
            "shape": -3.6203
          }
        },
        {
          "rank": 16,
          "number": "37291",
          "score": -7.266145,
          "sum": 22,
          "span": 8,
          "models": {
            "legacy": -9.9386,
            "markov": -9.6376,
            "bayes": -10.5946,
            "shape": -3.3673
          }
        },
        {
          "rank": 17,
          "number": "25291",
          "score": -7.266587,
          "sum": 19,
          "span": 8,
          "models": {
            "legacy": -9.4746,
            "markov": -10.2721,
            "bayes": -9.8403,
            "shape": -3.6203
          }
        },
        {
          "rank": 18,
          "number": "92293",
          "score": -7.270043,
          "sum": 25,
          "span": 7,
          "models": {
            "legacy": -9.3598,
            "markov": -10.6971,
            "bayes": -9.5246,
            "shape": -3.6203
          }
        },
        {
          "rank": 19,
          "number": "07233",
          "score": -7.27364,
          "sum": 15,
          "span": 7,
          "models": {
            "legacy": -10.1131,
            "markov": -10.0625,
            "bayes": -10.0058,
            "shape": -3.3673
          }
        },
        {
          "rank": 20,
          "number": "29713",
          "score": -7.274102,
          "sum": 22,
          "span": 8,
          "models": {
            "legacy": -9.593,
            "markov": -11.2843,
            "bayes": -9.2416,
            "shape": -3.3673
          }
        }
      ],
      "top3": [
        {
          "rank": 5,
          "number": "90193",
          "score": -7.041096,
          "sum": 22,
          "span": 9,
          "models": {
            "legacy": -9.545,
            "markov": -9.6056,
            "bayes": -9.842,
            "shape": -3.3673
          }
        },
        {
          "rank": 3,
          "number": "25213",
          "score": -7.400746,
          "sum": 13,
          "span": 4,
          "models": {
            "legacy": -10.3947,
            "markov": -10.6971,
            "bayes": -9.161,
            "shape": -3.6203
          }
        },
        {
          "rank": 4,
          "number": "27193",
          "score": -7.002298,
          "sum": 22,
          "span": 8,
          "models": {
            "legacy": -8.9706,
            "markov": -10.0625,
            "bayes": -9.7371,
            "shape": -3.3673
          }
        }
      ],
      "note": "随机开奖不可预测，本结果仅用于统计记录和复盘。"
    }
  }
}